tiktoktts/__init__.py
tiktoktts-1.2.dist-info/LICENSE
tiktoktts-1.2.dist-info/METADATA
tiktoktts-1.2.dist-info/WHEEL
tiktoktts-1.2.dist-info/top_level.txt
tiktoktts-1.2.dist-info/RECORD
