Metadata-Version: 2.1
Name: tiktoktts
Version: 1.2
Summary: Make a TikTok tts voices.
Home-page: https://github.com/gamertube583yt
Author: FlipFlapsRU
Author-email: ruslankidulin@gmail.com
License: MIT
License-File: LICENSE
